hostfactory/__init__.py
hostfactory/api.py
hostfactory/events.py
hostfactory/fsutils.py
hostfactory/hfcleaner.py
hostfactory/k8sutils.py
hostfactory/validator.py
hostfactory/cli/__init__.py
hostfactory/cli/context.py
hostfactory/cli/hf.py
hostfactory/cli/hfadmin.py
hostfactory/cli/log_handler.py
hostfactory/impl/__init__.py
hostfactory/impl/hfadmin.py
hostfactory/impl/watchers/__init__.py
hostfactory/impl/watchers/cluster.py
hostfactory/impl/watchers/kube_watcher.py
hostfactory/impl/watchers/node_watcher.py
hostfactory/impl/watchers/pod_watcher.py
hostfactory/impl/watchers/request.py
hostfactory/impl/watchers/request_machine.py
hostfactory/impl/watchers/return_machine.py
hostfactory/tests/__init__.py
hostfactory/tests/conftest.py
hostfactory/tests/regression/__init__.py
hostfactory/tests/regression/conftest.py
hostfactory/tests/regression/test_downsize.yaml
hostfactory/tests/regression/test_node_removal.yaml
hostfactory/tests/regression/test_rfb.yaml
hostfactory/tests/resources/eks-spec.yml
hostfactory/tests/resources/eks-templates.tpl
hostfactory/tests/resources/vanilla-spec.yml
hostfactory/tests/resources/vanilla-templates.tpl
hostfactory/tests/unit/__init__.py
hostfactory/tests/unit/conftest.py
hostfactory/tests/unit/test_api.py
hostfactory/tests/unit/test_events.py
hostfactory/tests/unit/test_hfcleaner.py
hostfactory/tests/unit/test_hostfactory.py
hostfactory/tests/unit/test_utils.py
hostfactory/tests/unit/test_watcher.py
hostfactory-1.0.2.dist-info/METADATA
hostfactory-1.0.2.dist-info/WHEEL
hostfactory-1.0.2.dist-info/entry_points.txt
hostfactory-1.0.2.dist-info/licenses/LICENSE
hostfactory-1.0.2.dist-info/licenses/NOTICE
hostfactory-1.0.2.dist-info/RECORD
