Metadata-Version: 2.4
Name: hostfactory
Version: 1.0.2
Summary: Symphony k8s deployment tools
License-File: LICENSE
License-File: NOTICE
Requires-Python: <=3.12.9,>=3.12
Requires-Dist: boto3
Requires-Dist: click>=8
Requires-Dist: hatchling
Requires-Dist: inotify
Requires-Dist: jinja2
Requires-Dist: kubernetes
Requires-Dist: pydantic
Requires-Dist: rich
Requires-Dist: setuptools-scm
Requires-Dist: tenacity
Requires-Dist: typing-extensions
Requires-Dist: wrapt
Provides-Extra: documentation
Requires-Dist: myst-parser; extra == 'documentation'
Requires-Dist: sphinx; extra == 'documentation'
Requires-Dist: sphinx-click; extra == 'documentation'
Provides-Extra: testing
Requires-Dist: coverage; extra == 'testing'
Requires-Dist: mypy; extra == 'testing'
Requires-Dist: pytest; extra == 'testing'
Requires-Dist: pytest-cov; extra == 'testing'
Requires-Dist: pyyaml; extra == 'testing'
Requires-Dist: ruff; extra == 'testing'
Requires-Dist: typos; extra == 'testing'
